LICENSE
README.md
setup.py
galleon/__init__.py
galleon/generator.py
galleon/samplers.py
galleon/settings.py
galleon/utils.py
galleon.egg-info/PKG-INFO
galleon.egg-info/SOURCES.txt
galleon.egg-info/dependency_links.txt
galleon.egg-info/requires.txt
galleon.egg-info/top_level.txt