Metadata-Version: 2.1
Name: galleon
Version: 1.0.0
Summary: Synthetic GW posterior catalog generator
Home-page: https://github.com/sterinaldi/galleon
Author: Stefano Rinaldi
Author-email: stefano.rinaldi@phd.unipi.it
Requires-Python: >=3.7
License-File: LICENSE
